pveagledemo/LICENSE
pveagledemo/eagle_demo_file.py
pveagledemo/eagle_demo_mic.py
pveagledemo-2.0.0.dist-info/METADATA
pveagledemo-2.0.0.dist-info/WHEEL
pveagledemo-2.0.0.dist-info/entry_points.txt
pveagledemo-2.0.0.dist-info/top_level.txt
pveagledemo-2.0.0.dist-info/RECORD
