Metadata-Version: 2.4
Name: pveagledemo
Version: 2.0.0
Summary: Eagle Speaker Recognition Engine demos
Home-page: https://github.com/Picovoice/eagle
Author: Picovoice
Author-email: hello@picovoice.ai
Keywords: Speaker Recognition,Speaker Identification,Voice Recognition,Voice Identification
Classifier: Development Status :: 5 - Production/Stable
Classifier: Intended Audience :: Developers
Classifier: License :: OSI Approved :: Apache Software License
Classifier: Operating System :: OS Independent
Classifier: Programming Language :: Python :: 3
Classifier: Topic :: Multimedia :: Sound/Audio :: Speech
Requires-Python: >=3.9
Requires-Dist: pveagle==2.0.0
Requires-Dist: pvrecorder==1.2.4
Dynamic: author
Dynamic: author-email
Dynamic: classifier
Dynamic: description
Dynamic: description-content-type
Dynamic: home-page
Dynamic: keywords
Dynamic: requires-dist
Dynamic: requires-python
Dynamic: summary
